simo/__init__.py
simo/asgi.py
simo/auto_update.py
simo/celeryc.py
simo/cli.py
simo/conf.py
simo/scripting.py
simo/settings.py
simo/urls.py
simo/_hub_template/hub/asgi.py
simo/_hub_template/hub/celeryc.py
simo/_hub_template/hub/manage.py
simo/_hub_template/hub/settings.py
simo/_hub_template/hub/urls.py
simo/core/__init__.py
simo/core/admin.py
simo/core/api.py
simo/core/api_auth.py
simo/core/app_widgets.py
simo/core/apps.py
simo/core/auto_urls.py
simo/core/autocomplete_views.py
simo/core/base_types.py
simo/core/context.py
simo/core/controllers.py
simo/core/dynamic_settings.py
simo/core/events.py
simo/core/filters.py
simo/core/forms.py
simo/core/gateways.py
simo/core/loggers.py
simo/core/middleware.py
simo/core/models.py
simo/core/permissions.py
simo/core/routing.py
simo/core/serializers.py
simo/core/signal_receivers.py
simo/core/socket_consumers.py
simo/core/storage.py
simo/core/tasks.py
simo/core/todos.py
simo/core/types.py
simo/core/views.py
simo/core/widgets.py
simo/core/db_backend/__init__.py
simo/core/db_backend/base.py
simo/core/management/__init__.py
simo/core/management/commands/__init__.py
simo/core/management/commands/gateways_manager.py
simo/core/management/commands/run_gateway.py
simo/core/management/commands/update.py
simo/core/migrations/0001_initial.py
simo/core/migrations/0002_load_icons.py
simo/core/migrations/0003_create_default_zones_and_categories.py
simo/core/migrations/0004_create_generic.py
simo/core/migrations/0005_component_subcomponents.py
simo/core/migrations/0006_alter_component_subcomponents.py
simo/core/migrations/0007_component_change_init_to.py
simo/core/migrations/0008_alter_component_change_init_to.py
simo/core/migrations/0009_auto_20220707_1404.py
simo/core/migrations/0010_historyaggregate.py
simo/core/migrations/0011_component_last_change.py
simo/core/migrations/0012_instance.py
simo/core/migrations/0013_auto_20231003_0754.py
simo/core/migrations/0014_zone_instance.py
simo/core/migrations/0015_auto_20231004_1113.py
simo-1.6.12.dist-info/LICENSE.md
simo-1.6.12.dist-info/METADATA
simo-1.6.12.dist-info/WHEEL
simo-1.6.12.dist-info/top_level.txt
simo-1.6.12.dist-info/RECORD
